setup.cfg
setup.py
cuber/__init__.py
cuber/__main__.py
cuber/cache.py
cuber/cube.py
cuber/cube_idle.py
cuber/cube_map.py
cuber/decorator.py
cuber/hyper_optimizer.py
cuber/model.py
cuber/utils.py
cuber/workflow.py
cuber.egg-info/PKG-INFO
cuber.egg-info/SOURCES.txt
cuber.egg-info/dependency_links.txt
cuber.egg-info/not-zip-safe
cuber.egg-info/requires.txt
cuber.egg-info/top_level.txt