Metadata-Version: 1.0
Name: cuber
Version: 1.0.35
Summary: Calculation-graph base
Home-page: https://github.com/kriot/Cuber
Author: Georgy Borisenko
Author-email: borisenko.gn@yandex.ru
License: GNU GPLv3
Platform: UNKNOWN
